documentation_search_enhanced/__init__.py
documentation_search_enhanced/__main__.py
documentation_search_enhanced/config.json
documentation_search_enhanced/config_manager.py
documentation_search_enhanced/config_validator.py
documentation_search_enhanced/content_enhancer.py
documentation_search_enhanced/docker_manager.py
documentation_search_enhanced/logger.py
documentation_search_enhanced/main.py
documentation_search_enhanced/project_generator.py
documentation_search_enhanced/project_scanner.py
documentation_search_enhanced/reranker.py
documentation_search_enhanced/site_index_builder.py
documentation_search_enhanced/site_index_downloader.py
documentation_search_enhanced/site_search.py
documentation_search_enhanced/smart_search.py
documentation_search_enhanced/snyk_integration.py
documentation_search_enhanced/vector_search.py
documentation_search_enhanced/version_resolver.py
documentation_search_enhanced/vulnerability_scanner.py
documentation_search_enhanced/web_scraper.py
documentation_search_enhanced-1.9.0.dist-info/METADATA
documentation_search_enhanced-1.9.0.dist-info/WHEEL
documentation_search_enhanced-1.9.0.dist-info/entry_points.txt
documentation_search_enhanced-1.9.0.dist-info/licenses/LICENSE
documentation_search_enhanced-1.9.0.dist-info/RECORD
