Metadata-Version: 2.4
Name: documentation-search-enhanced
Version: 1.9.0
Summary: Enhanced MCP server for searching documentation with OSINT vulnerability scanning, security analysis, and AWS-style deployment
Project-URL: Homepage, https://github.com/anton-prosterity/documentation-search-mcp
Project-URL: Repository, https://github.com/anton-prosterity/documentation-search-mcp
Project-URL: Issues, https://github.com/anton-prosterity/documentation-search-mcp/issues
Author-email: Anton Mishel <your-email@example.com>
License-Expression: MIT
License-File: LICENSE
Keywords: ai,assistant,documentation,fastapi,langchain,mcp,osint,osv,search,security,vulnerability
Classifier: Development Status :: 4 - Beta
Classifier: Intended Audience :: Developers
Classifier: License :: OSI Approved :: MIT License
Classifier: Programming Language :: Python :: 3
Classifier: Programming Language :: Python :: 3.12
Classifier: Programming Language :: Python :: 3.13
Classifier: Topic :: Internet :: WWW/HTTP :: Indexing/Search
Classifier: Topic :: Software Development :: Documentation
Requires-Python: >=3.12
Requires-Dist: beautifulsoup4>=4.13.4
Requires-Dist: httpx>=0.28.1
Requires-Dist: mcp[cli]>=1.23.0
Requires-Dist: playwright>=1.40.0
Requires-Dist: pydantic>=2.0
Requires-Dist: python-dotenv>=1.0.0
Requires-Dist: pyyaml>=6.0.1
Provides-Extra: dev
Requires-Dist: black>=23.0.0; extra == 'dev'
Requires-Dist: pytest-asyncio>=0.21.0; extra == 'dev'
Requires-Dist: pytest>=7.0.0; extra == 'dev'
Requires-Dist: ruff>=0.1.0; extra == 'dev'
Requires-Dist: twine>=4.0.0; extra == 'dev'
Provides-Extra: vector
Requires-Dist: faiss-cpu>=1.7.4; extra == 'vector'
Requires-Dist: numpy>=1.24.0; extra == 'vector'
Requires-Dist: sentence-transformers>=2.2.0; extra == 'vector'
